pygitbucket/__init__.py
pygitbucket/client.py
pygitbucket/exceptions.py
pygitbucket-2021.7.4.dist-info/LICENSE
pygitbucket-2021.7.4.dist-info/WHEEL
pygitbucket-2021.7.4.dist-info/METADATA
pygitbucket-2021.7.4.dist-info/RECORD
