Metadata-Version: 2.1
Name: pygitbucket
Version: 2021.7.4
Summary: This package enables you use the bitbucket REST-api using a simplified API
Home-page: https://github.com/SimiCode/pygitbucket
Keywords: bitbucket api python pygitbucket
Author: Edison Abahurire
Author-email: abahedison@gmail.com
Requires-Python: >=3.6
Classifier: Intended Audience :: Developers
Classifier: Development Status :: 4 - Beta
Classifier: Programming Language :: Python
Classifier: Programming Language :: Python :: 3.6
Classifier: Programming Language :: Python :: 3.7
Classifier: Programming Language :: Python :: 3.8
Classifier: Programming Language :: Python :: 3.9
Classifier: Topic :: Software Development :: Libraries :: Python Modules
Classifier: Programming Language :: Python :: Implementation :: CPython
Classifier: License :: OSI Approved :: MIT License
Requires-Dist: requests
Project-URL: Bug-Tracker, https://github.com/SimiCode/pygitbucket/issues
Project-URL: Documentation, https://github.com/SimiCode/pygitbucket/README.md
Project-URL: Source-Code, https://github.com/SimiCode/pygitbucket/bitbucket
